autoseeder_cli/__init__.py
autoseeder_cli/as_cli_actions.py
autoseeder_cli/util.py
autoseeder_cli-3.1.0.dist-info/METADATA
autoseeder_cli-3.1.0.dist-info/WHEEL
autoseeder_cli-3.1.0.dist-info/entry_points.txt
autoseeder_cli-3.1.0.dist-info/top_level.txt
autoseeder_cli-3.1.0.dist-info/RECORD
