Metadata-Version: 2.1
Name: autoseeder-cli
Version: 3.1.0
Summary: Autoseeder CLI tool
Home-page: https://cosive.com
Author: Cosive
Author-email: info@cosive.com
License: Apache 2.0
Keywords: Autoseeder
Platform: UNKNOWN
Classifier: Development Status :: 3 - Alpha
Classifier: Intended Audience :: Developers
Classifier: License :: OSI Approved :: Apache Software License
Classifier: Programming Language :: Python :: 3.6
Requires-Dist: docopt (~=0.6.2)
Requires-Dist: environs (~=9.2.0)
Requires-Dist: requests (~=2.25.0)
Requires-Dist: loguru (~=0.5.3)
Provides-Extra: test
Requires-Dist: mock (==4.0.2) ; extra == 'test'
Requires-Dist: tox (>=3.20) ; extra == 'test'
